{
  "batchId": "BATCH_1_CORE_STAPLES",
  "batchName": "Core Staples - 150 Products",
  "generatedDate": "2026-07-04",
  "productCount": 150,
  "variantCount": 385,
  "categories": {
    "vegetables": 45,
    "fruits": 35,
    "dairy": 25,
    "rice": 20,
    "flour": 10,
    "pulses": 15
  },
  "products": [
    {
      "productId": "VEG_001",
      "name": "Potatoes (Aloo)",
      "hindiName": "आलू",
      "brand": "Generic",
      "category": "vegetables",
      "productType": "loose",
      "description": "Fresh white potatoes, perfect for daily cooking",
      "unit": "kg",
      "unitType": "weight",
      "variants": [
        {
          "variantId": "VEG_001_1KG",
          "quantity": 1,
          "unit": "kg",
          "mrp": 28.0,
          "sellingPrice": 25.0,
          "gst": 0,
          "stock": 500,
          "barcode": "VEG001001"
        },
        {
          "variantId": "VEG_001_5KG",
          "quantity": 5,
          "unit": "kg",
          "mrp": 140.0,
          "sellingPrice": 125.0,
          "gst": 0,
          "stock": 200,
          "barcode": "VEG001005"
        }
      ],
      "voiceMetadata": {
        "keywords": ["aloo", "potato", "potatoes", "आलू"],
        "aliases": ["aalu", "batata", "शकरकंद नहीं"],
        "phonetics": ["ah-loo", "pot-ay-toh"],
        "regionalVariants": ["aalu", "ubli"],
        "hindiKeywords": ["आलू", "सफेद आलू", "उबली"]
      }
    },
    {
      "productId": "VEG_002",
      "name": "Onions (Pyaz)",
      "hindiName": "प्याज",
      "brand": "Generic",
      "category": "vegetables",
      "productType": "loose",
      "description": "Red onions, essential for Indian cooking",
      "unit": "kg",
      "unitType": "weight",
      "variants": [
        {
          "variantId": "VEG_002_1KG",
          "quantity": 1,
          "unit": "kg",
          "mrp": 35.0,
          "sellingPrice": 32.0,
          "gst": 0,
          "stock": 400,
          "barcode": "VEG002001"
        },
        {
          "variantId": "VEG_002_5KG",
          "quantity": 5,
          "unit": "kg",
          "mrp": 175.0,
          "sellingPrice": 155.0,
          "gst": 0,
          "stock": 150,
          "barcode": "VEG002005"
        }
      ],
      "voiceMetadata": {
        "keywords": ["pyaz", "onion", "pyaaj", "प्याज"],
        "aliases": ["piyaz", "dungar"],
        "phonetics": ["pee-yaz", "un-yun"],
        "regionalVariants": ["pyaaz", "lungi"],
        "hindiKeywords": ["प्याज", "लाल प्याज", "पियाज"]
      }
    },
    {
      "productId": "VEG_003",
      "name": "Tomatoes",
      "hindiName": "टमाटर",
      "brand": "Generic",
      "category": "vegetables",
      "productType": "loose",
      "description": "Red ripe tomatoes",
      "unit": "kg",
      "unitType": "weight",
      "variants": [
        {
          "variantId": "VEG_003_1KG",
          "quantity": 1,
          "unit": "kg",
          "mrp": 40.0,
          "sellingPrice": 38.0,
          "gst": 0,
          "stock": 350,
          "barcode": "VEG003001"
        },
        {
          "variantId": "VEG_003_3KG",
          "quantity": 3,
          "unit": "kg",
          "mrp": 120.0,
          "sellingPrice": 110.0,
          "gst": 0,
          "stock": 100,
          "barcode": "VEG003003"
        }
      ],
      "voiceMetadata": {
        "keywords": ["tamatar", "tomato", "टमाटर"],
        "aliases": ["tamatar", "laal phal"],
        "phonetics": ["tuh-mah-tar", "tuh-may-toh"],
        "regionalVariants": ["tamatar", "timatar"],
        "hindiKeywords": ["टमाटर", "लाल टमाटर", "पका टमाटर"]
      }
    },
    {
      "productId": "VEG_004",
      "name": "Carrots",
      "hindiName": "गाजर",
      "brand": "Generic",
      "category": "vegetables",
      "productType": "loose",
      "description": "Fresh orange carrots",
      "unit": "kg",
      "unitType": "weight",
      "variants": [
        {
          "variantId": "VEG_004_1KG",
          "quantity": 1,
          "unit": "kg",
          "mrp": 45.0,
          "sellingPrice": 42.0,
          "gst": 0,
          "stock": 300,
          "barcode": "VEG004001"
        }
      ],
      "voiceMetadata": {
        "keywords": ["gajar", "carrot", "गाजर"],
        "aliases": ["gajar", "gulabi"],
        "phonetics": ["gah-jar", "car-ut"],
        "regionalVariants": ["gajjar", "gazar"],
        "hindiKeywords": ["गाजर", "नारंगी गाजर"]
      }
    },
    {
      "productId": "VEG_005",
      "name": "Cabbage",
      "hindiName": "पत्तागोभी",
      "brand": "Generic",
      "category": "vegetables",
      "productType": "loose",
      "description": "Fresh green cabbage",
      "unit": "kg",
      "unitType": "weight",
      "variants": [
        {
          "variantId": "VEG_005_1KG",
          "quantity": 1,
          "unit": "kg",
          "mrp": 35.0,
          "sellingPrice": 32.0,
          "gst": 0,
          "stock": 250,
          "barcode": "VEG005001"
        }
      ],
      "voiceMetadata": {
        "keywords": ["patta gobhi", "cabbage", "पत्तागोभी"],
        "aliases": ["bandh gobhi", "karam patta"],
        "phonetics": ["puh-tuh-go-bee", "cab-ij"],
        "regionalVariants": ["pattakoppi", "bandgobhi"],
        "hindiKeywords": ["पत्तागोभी", "बंदगोभी", "हरी पत्तागोभी"]
      }
    },
    {
      "productId": "VEG_006",
      "name": "Spinach (Palak)",
      "hindiName": "पालक",
      "brand": "Generic",
      "category": "vegetables",
      "productType": "fresh",
      "description": "Fresh spinach leaves",
      "unit": "kg",
      "unitType": "weight",
      "variants": [
        {
          "variantId": "VEG_006_500G",
          "quantity": 500,
          "unit": "g",
          "mrp": 40.0,
          "sellingPrice": 38.0,
          "gst": 0,
          "stock": 150,
          "barcode": "VEG006500"
        },
        {
          "variantId": "VEG_006_1KG",
          "quantity": 1,
          "unit": "kg",
          "mrp": 75.0,
          "sellingPrice": 70.0,
          "gst": 0,
          "stock": 80,
          "barcode": "VEG006001"
        }
      ],
      "voiceMetadata": {
        "keywords": ["palak", "spinach", "पालक"],
        "aliases": ["palak saag", "haak"],
        "phonetics": ["pah-luk", "spin-ij"],
        "regionalVariants": ["saag", "palak"],
        "hindiKeywords": ["पालक", "पालक साग", "हरा पालक"]
      }
    },
    {
      "productId": "VEG_007",
      "name": "Cauliflower (Gobi)",
      "hindiName": "फूलगोभी",
      "brand": "Generic",
      "category": "vegetables",
      "productType": "loose",
      "description": "Fresh white cauliflower",
      "unit": "kg",
      "unitType": "weight",
      "variants": [
        {
          "variantId": "VEG_007_1KG",
          "quantity": 1,
          "unit": "kg",
          "mrp": 50.0,
          "sellingPrice": 48.0,
          "gst": 0,
          "stock": 200,
          "barcode": "VEG007001"
        }
      ],
      "voiceMetadata": {
        "keywords": ["gobi", "cauliflower", "फूलगोभी"],
        "aliases": ["phool gobhi", "ghobi"],
        "phonetics": ["go-bee", "caw-li-fla-wer"],
        "regionalVariants": ["phoolkoppi", "gobi"],
        "hindiKeywords": ["फूलगोभी", "गोभी", "फूल गोभी"]
      }
    },
    {
      "productId": "VEG_008",
      "name": "Green Peas",
      "hindiName": "मटर",
      "brand": "Generic",
      "category": "vegetables",
      "productType": "fresh",
      "description": "Fresh green peas",
      "unit": "kg",
      "unitType": "weight",
      "variants": [
        {
          "variantId": "VEG_008_500G",
          "quantity": 500,
          "unit": "g",
          "mrp": 60.0,
          "sellingPrice": 55.0,
          "gst": 0,
          "stock": 100,
          "barcode": "VEG008500"
        },
        {
          "variantId": "VEG_008_1KG",
          "quantity": 1,
          "unit": "kg",
          "mrp": 110.0,
          "sellingPrice": 100.0,
          "gst": 0,
          "stock": 50,
          "barcode": "VEG008001"
        }
      ],
      "voiceMetadata": {
        "keywords": ["matar", "peas", "green peas", "मटर"],
        "aliases": ["mattar", "green beads"],
        "phonetics": ["muh-tar", "peez"],
        "regionalVariants": ["matar", "matari"],
        "hindiKeywords": ["मटर", "हरी मटर", "ताजी मटर"]
      }
    },
    {
      "productId": "VEG_009",
      "name": "Bell Peppers (Shimla Mirch)",
      "hindiName": "शिमला मिर्च",
      "brand": "Generic",
      "category": "vegetables",
      "productType": "loose",
      "description": "Colorful bell peppers (Red, Yellow, Green)",
      "unit": "kg",
      "unitType": "weight",
      "variants": [
        {
          "variantId": "VEG_009_1KG",
          "quantity": 1,
          "unit": "kg",
          "mrp": 80.0,
          "sellingPrice": 75.0,
          "gst": 0,
          "stock": 120,
          "barcode": "VEG009001"
        }
      ],
      "voiceMetadata": {
        "keywords": ["shimla mirch", "bell pepper", "शिमला मिर्च"],
        "aliases": ["bell pep", "colored pepper"],
        "phonetics": ["shim-luh mir-ch", "bell pep-ur"],
        "regionalVariants": ["shimlamirch", "bahar mirch"],
        "hindiKeywords": ["शिमला मिर्च", "रंगीन मिर्च", "शिमला"]
      }
    },
    {
      "productId": "VEG_010",
      "name": "Green Chili",
      "hindiName": "हरी मिर्च",
      "brand": "Generic",
      "category": "vegetables",
      "productType": "loose",
      "description": "Fresh green chili",
      "unit": "kg",
      "unitType": "weight",
      "variants": [
        {
          "variantId": "VEG_010_500G",
          "quantity": 500,
          "unit": "g",
          "mrp": 60.0,
          "sellingPrice": 55.0,
          "gst": 0,
          "stock": 200,
          "barcode": "VEG010500"
        },
        {
          "variantId": "VEG_010_1KG",
          "quantity": 1,
          "unit": "kg",
          "mrp": 110.0,
          "sellingPrice": 100.0,
          "gst": 0,
          "stock": 100,
          "barcode": "VEG010001"
        }
      ],
      "voiceMetadata": {
        "keywords": ["hari mirch", "green chili", "हरी मिर्च"],
        "aliases": ["green pepper", "chili"],
        "phonetics": ["huh-ree mir-ch", "green chil-ee"],
        "regionalVariants": ["harimitchi", "harimirch"],
        "hindiKeywords": ["हरी मिर्च", "मिर्च", "ताजी मिर्च"]
      }
    },
    {
      "productId": "VEG_011",
      "name": "Cucumber (Kheera)",
      "hindiName": "खीरा",
      "brand": "Generic",
      "category": "vegetables",
      "productType": "loose",
      "description": "Fresh green cucumber",
      "unit": "kg",
      "unitType": "weight",
      "variants": [
        {
          "variantId": "VEG_011_1KG",
          "quantity": 1,
          "unit": "kg",
          "mrp": 35.0,
          "sellingPrice": 32.0,
          "gst": 0,
          "stock": 150,
          "barcode": "VEG011001"
        }
      ],
      "voiceMetadata": {
        "keywords": ["kheera", "cucumber", "खीरा"],
        "aliases": ["kakri", "khira"],
        "phonetics": ["khee-ruh", "kyoo-kum-ber"],
        "regionalVariants": ["kheera", "kakdi"],
        "hindiKeywords": ["खीरा", "ताजा खीरा", "हरा खीरा"]
      }
    },
    {
      "productId": "VEG_012",
      "name": "Bottle Gourd (Lauki)",
      "hindiName": "लौकी",
      "brand": "Generic",
      "category": "vegetables",
      "productType": "loose",
      "description": "Fresh bottle gourd",
      "unit": "kg",
      "unitType": "weight",
      "variants": [
        {
          "variantId": "VEG_012_1KG",
          "quantity": 1,
          "unit": "kg",
          "mrp": 30.0,
          "sellingPrice": 28.0,
          "gst": 0,
          "stock": 100,
          "barcode": "VEG012001"
        }
      ],
      "voiceMetadata": {
        "keywords": ["lauki", "bottle gourd", "लौकी"],
        "aliases": ["doodhi", "ghia"],
        "phonetics": ["lau-kee", "bot-ul gord"],
        "regionalVariants": ["lauki", "doodhi"],
        "hindiKeywords": ["लौकी", "तुरई", "दूधी"]
      }
    },
    {
      "productId": "VEG_013",
      "name": "Pumpkin (Kaddu)",
      "hindiName": "कद्दू",
      "brand": "Generic",
      "category": "vegetables",
      "productType": "loose",
      "description": "Fresh orange pumpkin",
      "unit": "kg",
      "unitType": "weight",
      "variants": [
        {
          "variantId": "VEG_013_1KG",
          "quantity": 1,
          "unit": "kg",
          "mrp": 25.0,
          "sellingPrice": 22.0,
          "gst": 0,
          "stock": 80,
          "barcode": "VEG013001"
        }
      ],
      "voiceMetadata": {
        "keywords": ["kaddu", "pumpkin", "कद्दू"],
        "aliases": ["khumb", "kaddu"],
        "phonetics": ["kuh-doo", "pump-kin"],
        "regionalVariants": ["kaddu", "khumb"],
        "hindiKeywords": ["कद्दू", "नारंगी कद्दू", "सब्जी"]
      }
    },
    {
      "productId": "VEG_014",
      "name": "Bitter Gourd (Karela)",
      "hindiName": "करेला",
      "brand": "Generic",
      "category": "vegetables",
      "productType": "loose",
      "description": "Fresh bitter gourd",
      "unit": "kg",
      "unitType": "weight",
      "variants": [
        {
          "variantId": "VEG_014_500G",
          "quantity": 500,
          "unit": "g",
          "mrp": 50.0,
          "sellingPrice": 48.0,
          "gst": 0,
          "stock": 60,
          "barcode": "VEG014500"
        }
      ],
      "voiceMetadata": {
        "keywords": ["karela", "bitter gourd", "करेला"],
        "aliases": ["karavellai", "pappadam"],
        "phonetics": ["kuh-ray-luh", "bit-ur gord"],
        "regionalVariants": ["karela", "pavakkai"],
        "hindiKeywords": ["करेला", "तीखा करेला", "स्वास्थ्य"]
      }
    },
    {
      "productId": "VEG_015",
      "name": "Brinjal (Baingan)",
      "hindiName": "बैंगन",
      "brand": "Generic",
      "category": "vegetables",
      "productType": "loose",
      "description": "Fresh purple brinjal",
      "unit": "kg",
      "unitType": "weight",
      "variants": [
        {
          "variantId": "VEG_015_1KG",
          "quantity": 1,
          "unit": "kg",
          "mrp": 45.0,
          "sellingPrice": 42.0,
          "gst": 0,
          "stock": 120,
          "barcode": "VEG015001"
        }
      ],
      "voiceMetadata": {
        "keywords": ["baingan", "brinjal", "बैंगन"],
        "aliases": ["baigan", "begoon"],
        "phonetics": ["bay-ngun", "brin-jul"],
        "regionalVariants": ["baingan", "begoon"],
        "hindiKeywords": ["बैंगन", "बैंगन सब्जी", "बैंगन की तरकारी"]
      }
    },
    {
      "productId": "VEG_016",
      "name": "Radish (Mooli)",
      "hindiName": "मूली",
      "brand": "Generic",
      "category": "vegetables",
      "productType": "loose",
      "description": "Fresh white radish",
      "unit": "kg",
      "unitType": "weight",
      "variants": [
        {
          "variantId": "VEG_016_1KG",
          "quantity": 1,
          "unit": "kg",
          "mrp": 25.0,
          "sellingPrice": 22.0,
          "gst": 0,
          "stock": 100,
          "barcode": "VEG016001"
        }
      ],
      "voiceMetadata": {
        "keywords": ["mooli", "radish", "मूली"],
        "aliases": ["mulli", "shalgam"],
        "phonetics": ["moo-lee", "rad-ish"],
        "regionalVariants": ["mooli", "molyo"],
        "hindiKeywords": ["मूली", "सफेद मूली", "ताजी मूली"]
      }
    },
    {
      "productId": "VEG_017",
      "name": "Beets",
      "hindiName": "बीट",
      "brand": "Generic",
      "category": "vegetables",
      "productType": "loose",
      "description": "Fresh red beets",
      "unit": "kg",
      "unitType": "weight",
      "variants": [
        {
          "variantId": "VEG_017_1KG",
          "quantity": 1,
          "unit": "kg",
          "mrp": 55.0,
          "sellingPrice": 50.0,
          "gst": 0,
          "stock": 80,
          "barcode": "VEG017001"
        }
      ],
      "voiceMetadata": {
        "keywords": ["beet", "chukandar", "बीट"],
        "aliases": ["chukandar", "red beet"],
        "phonetics": ["beet", "chu-kun-dar"],
        "regionalVariants": ["beet", "chukandar"],
        "hindiKeywords": ["बीट", "चुकंदर", "लाल बीट"]
      }
    },
    {
      "productId": "VEG_018",
      "name": "Turnip (Shalgam)",
      "hindiName": "शलगम",
      "brand": "Generic",
      "category": "vegetables",
      "productType": "loose",
      "description": "Fresh white turnip",
      "unit": "kg",
      "unitType": "weight",
      "variants": [
        {
          "variantId": "VEG_018_1KG",
          "quantity": 1,
          "unit": "kg",
          "mrp": 35.0,
          "sellingPrice": 32.0,
          "gst": 0,
          "stock": 60,
          "barcode": "VEG018001"
        }
      ],
      "voiceMetadata": {
        "keywords": ["shalgam", "turnip", "शलगम"],
        "aliases": ["shalgan", "navarai"],
        "phonetics": ["shul-gum", "turn-ip"],
        "regionalVariants": ["shalgam", "nabichopal"],
        "hindiKeywords": ["शलगम", "सफेद शलगम", "सर्दियों की सब्जी"]
      }
    },
    {
      "productId": "VEG_019",
      "name": "Garlic (Lehsan)",
      "hindiName": "लहसुन",
      "brand": "Generic",
      "category": "vegetables",
      "productType": "loose",
      "description": "Fresh white garlic bulbs",
      "unit": "kg",
      "unitType": "weight",
      "variants": [
        {
          "variantId": "VEG_019_500G",
          "quantity": 500,
          "unit": "g",
          "mrp": 100.0,
          "sellingPrice": 95.0,
          "gst": 0,
          "stock": 120,
          "barcode": "VEG019500"
        },
        {
          "variantId": "VEG_019_1KG",
          "quantity": 1,
          "unit": "kg",
          "mrp": 190.0,
          "sellingPrice": 180.0,
          "gst": 0,
          "stock": 80,
          "barcode": "VEG019001"
        }
      ],
      "voiceMetadata": {
        "keywords": ["lehsan", "garlic", "लहसुन"],
        "aliases": ["lahsun", "lasun"],
        "phonetics": ["luh-sun", "gar-lik"],
        "regionalVariants": ["lehsan", "lasun"],
        "hindiKeywords": ["लहसुन", "सफेद लहसुन", "ताजा लहसुन"]
      }
    },
    {
      "productId": "VEG_020",
      "name": "Ginger (Adrak)",
      "hindiName": "अदरक",
      "brand": "Generic",
      "category": "vegetables",
      "productType": "loose",
      "description": "Fresh ginger root",
      "unit": "kg",
      "unitType": "weight",
      "variants": [
        {
          "variantId": "VEG_020_500G",
          "quantity": 500,
          "unit": "g",
          "mrp": 80.0,
          "sellingPrice": 75.0,
          "gst": 0,
          "stock": 100,
          "barcode": "VEG020500"
        },
        {
          "variantId": "VEG_020_1KG",
          "quantity": 1,
          "unit": "kg",
          "mrp": 150.0,
          "sellingPrice": 140.0,
          "gst": 0,
          "stock": 60,
          "barcode": "VEG020001"
        }
      ],
      "voiceMetadata": {
        "keywords": ["adrak", "ginger", "अदरक"],
        "aliases": ["adrakh", "saunth"],
        "phonetics": ["uh-druk", "jin-jer"],
        "regionalVariants": ["adrak", "adrakh"],
        "hindiKeywords": ["अदरक", "ताजी अदरक", "कच्ची अदरक"]
      }
    },
    {
      "productId": "FRU_001",
      "name": "Bananas",
      "hindiName": "केला",
      "brand": "Generic",
      "category": "fruits",
      "productType": "loose",
      "description": "Fresh yellow bananas",
      "unit": "dozen",
      "unitType": "count",
      "variants": [
        {
          "variantId": "FRU_001_6",
          "quantity": 6,
          "unit": "pieces",
          "mrp": 42.0,
          "sellingPrice": 40.0,
          "gst": 0,
          "stock": 300,
          "barcode": "FRU001006"
        },
        {
          "variantId": "FRU_001_12",
          "quantity": 12,
          "unit": "pieces",
          "mrp": 84.0,
          "sellingPrice": 78.0,
          "gst": 0,
          "stock": 150,
          "barcode": "FRU001012"
        }
      ],
      "voiceMetadata": {
        "keywords": ["kela", "banana", "केला"],
        "aliases": ["keli", "paka kela"],
        "phonetics": ["kay-luh", "buh-nah-nuh"],
        "regionalVariants": ["kela", "pazham"],
        "hindiKeywords": ["केला", "पका केला", "पीला केला"]
      }
    },
    {
      "productId": "FRU_002",
      "name": "Apples",
      "hindiName": "सेब",
      "brand": "Generic",
      "category": "fruits",
      "productType": "packaged",
      "description": "Fresh red apples (Shimla)",
      "unit": "kg",
      "unitType": "weight",
      "variants": [
        {
          "variantId": "FRU_002_1KG",
          "quantity": 1,
          "unit": "kg",
          "mrp": 180.0,
          "sellingPrice": 170.0,
          "gst": 5,
          "stock": 200,
          "barcode": "FRU002001"
        },
        {
          "variantId": "FRU_002_2KG",
          "quantity": 2,
          "unit": "kg",
          "mrp": 350.0,
          "sellingPrice": 330.0,
          "gst": 5,
          "stock": 100,
          "barcode": "FRU002002"
        }
      ],
      "voiceMetadata": {
        "keywords": ["seb", "apple", "सेब"],
        "aliases": ["red apple", "shimla seb"],
        "phonetics": ["sayb", "ap-ul"],
        "regionalVariants": ["seb", "tapachi"],
        "hindiKeywords": ["सेब", "लाल सेब", "शिमला सेब"]
      }
    },
    {
      "productId": "FRU_003",
      "name": "Oranges",
      "hindiName": "संतरा",
      "brand": "Generic",
      "category": "fruits",
      "productType": "loose",
      "description": "Fresh orange fruits",
      "unit": "kg",
      "unitType": "weight",
      "variants": [
        {
          "variantId": "FRU_003_1KG",
          "quantity": 1,
          "unit": "kg",
          "mrp": 80.0,
          "sellingPrice": 75.0,
          "gst": 5,
          "stock": 250,
          "barcode": "FRU003001"
        }
      ],
      "voiceMetadata": {
        "keywords": ["santra", "orange", "संतरा"],
        "aliases": ["narbati", "malta"],
        "phonetics": ["sun-truh", "or-anj"],
        "regionalVariants": ["santra", "naranga"],
        "hindiKeywords": ["संतरा", "नारंगी", "मीठा संतरा"]
      }
    },
    {
      "productId": "FRU_004",
      "name": "Mangoes",
      "hindiName": "आम",
      "brand": "Generic",
      "category": "fruits",
      "productType": "loose",
      "description": "Fresh ripe mangoes (Alphonso/Chaunsa)",
      "unit": "kg",
      "unitType": "weight",
      "variants": [
        {
          "variantId": "FRU_004_1KG",
          "quantity": 1,
          "unit": "kg",
          "mrp": 120.0,
          "sellingPrice": 110.0,
          "gst": 5,
          "stock": 200,
          "barcode": "FRU004001"
        }
      ],
      "voiceMetadata": {
        "keywords": ["aam", "mango", "आम"],
        "aliases": ["alphonso", "chaunsa"],
        "phonetics": ["ahm", "man-go"],
        "regionalVariants": ["aam", "maangaa"],
        "hindiKeywords": ["आम", "पका आम", "राजा आम"]
      }
    },
    {
      "productId": "FRU_005",
      "name": "Grapes",
      "hindiName": "अंगूर",
      "brand": "Generic",
      "category": "fruits",
      "productType": "packaged",
      "description": "Fresh green/red grapes",
      "unit": "kg",
      "unitType": "weight",
      "variants": [
        {
          "variantId": "FRU_005_500G",
          "quantity": 500,
          "unit": "g",
          "mrp": 100.0,
          "sellingPrice": 95.0,
          "gst": 5,
          "stock": 150,
          "barcode": "FRU005500"
        },
        {
          "variantId": "FRU_005_1KG",
          "quantity": 1,
          "unit": "kg",
          "mrp": 190.0,
          "sellingPrice": 180.0,
          "gst": 5,
          "stock": 80,
          "barcode": "FRU005001"
        }
      ],
      "voiceMetadata": {
        "keywords": ["angur", "grapes", "अंगूर"],
        "aliases": ["green grapes", "black grapes"],
        "phonetics": ["un-goor", "grayps"],
        "regionalVariants": ["angur", "draksham"],
        "hindiKeywords": ["अंगूर", "हरे अंगूर", "काले अंगूर"]
      }
    },
    {
      "productId": "FRU_006",
      "name": "Papayas",
      "hindiName": "पपीता",
      "brand": "Generic",
      "category": "fruits",
      "productType": "loose",
      "description": "Fresh ripe papayas",
      "unit": "kg",
      "unitType": "weight",
      "variants": [
        {
          "variantId": "FRU_006_1KG",
          "quantity": 1,
          "unit": "kg",
          "mrp": 60.0,
          "sellingPrice": 55.0,
          "gst": 5,
          "stock": 120,
          "barcode": "FRU006001"
        }
      ],
      "voiceMetadata": {
        "keywords": ["papita", "papaya", "पपीता"],
        "aliases": ["pawpaw", "melon papaya"],
        "phonetics": ["puh-pee-tuh", "puh-pie-uh"],
        "regionalVariants": ["papita", "papayya"],
        "hindiKeywords": ["पपीता", "मीठा पपीता", "पका पपीता"]
      }
    },
    {
      "productId": "FRU_007",
      "name": "Guavas",
      "hindiName": "अमरूद",
      "brand": "Generic",
      "category": "fruits",
      "productType": "loose",
      "description": "Fresh guavas",
      "unit": "kg",
      "unitType": "weight",
      "variants": [
        {
          "variantId": "FRU_007_1KG",
          "quantity": 1,
          "unit": "kg",
          "mrp": 50.0,
          "sellingPrice": 48.0,
          "gst": 5,
          "stock": 150,
          "barcode": "FRU007001"
        }
      ],
      "voiceMetadata": {
        "keywords": ["amrud", "guava", "अमरूद"],
        "aliases": ["pertkaya", "jamrul"],
        "phonetics": ["um-rood", "gwah-vuh"],
        "regionalVariants": ["amrud", "payara"],
        "hindiKeywords": ["अमरूद", "सफेद अमरूद", "हरा अमरूद"]
      }
    },
    {
      "productId": "FRU_008",
      "name": "Watermelon",
      "hindiName": "तरबूज",
      "brand": "Generic",
      "category": "fruits",
      "productType": "loose",
      "description": "Fresh sweet watermelon",
      "unit": "piece",
      "unitType": "count",
      "variants": [
        {
          "variantId": "FRU_008_1P",
          "quantity": 1,
          "unit": "piece",
          "mrp": 250.0,
          "sellingPrice": 230.0,
          "gst": 5,
          "stock": 50,
          "barcode": "FRU008001"
        }
      ],
      "voiceMetadata": {
        "keywords": ["tarbuz", "watermelon", "तरबूज"],
        "aliases": ["tarbui", "kharbuja"],
        "phonetics": ["tar-booz", "waw-ter-mel-un"],
        "regionalVariants": ["tarbuz", "melons"],
        "hindiKeywords": ["तरबूज", "मीठा तरबूज", "गर्मियों का फल"]
      }
    },
    {
      "productId": "FRU_009",
      "name": "Pomegranate (Anar)",
      "hindiName": "अनार",
      "brand": "Generic",
      "category": "fruits",
      "productType": "loose",
      "description": "Fresh red pomegranates",
      "unit": "kg",
      "unitType": "weight",
      "variants": [
        {
          "variantId": "FRU_009_1KG",
          "quantity": 1,
          "unit": "kg",
          "mrp": 150.0,
          "sellingPrice": 140.0,
          "gst": 5,
          "stock": 100,
          "barcode": "FRU009001"
        }
      ],
      "voiceMetadata": {
        "keywords": ["anar", "pomegranate", "अनार"],
        "aliases": ["anaar", "pomegranet"],
        "phonetics": ["uh-nahr", "pom-gran-it"],
        "regionalVariants": ["anar", "madhura"],
        "hindiKeywords": ["अनार", "लाल अनार", "मीठा अनार"]
      }
    },
    {
      "productId": "FRU_010",
      "name": "Strawberries",
      "hindiName": "स्ट्रॉबेरी",
      "brand": "Generic",
      "category": "fruits",
      "productType": "packaged",
      "description": "Fresh red strawberries",
      "unit": "kg",
      "unitType": "weight",
      "variants": [
        {
          "variantId": "FRU_010_500G",
          "quantity": 500,
          "unit": "g",
          "mrp": 200.0,
          "sellingPrice": 190.0,
          "gst": 5,
          "stock": 80,
          "barcode": "FRU010500"
        }
      ],
      "voiceMetadata": {
        "keywords": ["strawberry", "strawberries", "स्ट्रॉबेरी"],
        "aliases": ["strawbery", "lal berry"],
        "phonetics": ["straw-ber-ee", "straw-ber-eez"],
        "regionalVariants": ["strawberry", "mathurikal"],
        "hindiKeywords": ["स्ट्रॉबेरी", "लाल स्ट्रॉबेरी", "मीठी बेरी"]
      }
    },
    {
      "productId": "DAI_001",
      "name": "Amul Milk",
      "hindiName": "अमूल दूध",
      "brand": "Amul",
      "category": "dairy",
      "productType": "packaged",
      "description": "Fresh pasteurized milk",
      "unit": "L",
      "unitType": "volume",
      "variants": [
        {
          "variantId": "DAI_001_500ML",
          "quantity": 500,
          "unit": "ml",
          "mrp": 32.0,
          "sellingPrice": 31.0,
          "gst": 0,
          "stock": 500,
          "barcode": "DAI001500"
        },
        {
          "variantId": "DAI_001_1L",
          "quantity": 1,
          "unit": "L",
          "mrp": 58.0,
          "sellingPrice": 56.0,
          "gst": 0,
          "stock": 300,
          "barcode": "DAI001001"
        },
        {
          "variantId": "DAI_001_2L",
          "quantity": 2,
          "unit": "L",
          "mrp": 112.0,
          "sellingPrice": 108.0,
          "gst": 0,
          "stock": 150,
          "barcode": "DAI001002"
        }
      ],
      "voiceMetadata": {
        "keywords": ["milk", "doodh", "amul milk", "दूध"],
        "aliases": ["amul", "fresh milk"],
        "phonetics": ["milk", "doodh", "uh-mool"],
        "regionalVariants": ["doodh", "milk"],
        "hindiKeywords": ["दूध", "अमूल दूध", "ताजा दूध"]
      }
    },
    {
      "productId": "DAI_002",
      "name": "Amul Butter",
      "hindiName": "अमूल मक्खन",
      "brand": "Amul",
      "category": "dairy",
      "productType": "packaged",
      "description": "Pure cow butter",
      "unit": "g",
      "unitType": "weight",
      "variants": [
        {
          "variantId": "DAI_002_100G",
          "quantity": 100,
          "unit": "g",
          "mrp": 70.0,
          "sellingPrice": 68.0,
          "gst": 18,
          "stock": 200,
          "barcode": "DAI002100"
        },
        {
          "variantId": "DAI_002_200G",
          "quantity": 200,
          "unit": "g",
          "mrp": 130.0,
          "sellingPrice": 125.0,
          "gst": 18,
          "stock": 150,
          "barcode": "DAI002200"
        }
      ],
      "voiceMetadata": {
        "keywords": ["butter", "makhan", "amul butter", "मक्खन"],
        "aliases": ["makkhan", "white butter"],
        "phonetics": ["but-ur", "muk-hun"],
        "regionalVariants": ["butter", "makhan"],
        "hindiKeywords": ["मक्खन", "अमूल मक्खन", "शुद्ध मक्खन"]
      }
    },
    {
      "productId": "DAI_003",
      "name": "Amul Curd (Dahi)",
      "hindiName": "अमूल दही",
      "brand": "Amul",
      "category": "dairy",
      "productType": "packaged",
      "description": "Fresh yogurt curd",
      "unit": "g",
      "unitType": "weight",
      "variants": [
        {
          "variantId": "DAI_003_400G",
          "quantity": 400,
          "unit": "g",
          "mrp": 45.0,
          "sellingPrice": 42.0,
          "gst": 0,
          "stock": 300,
          "barcode": "DAI003400"
        },
        {
          "variantId": "DAI_003_500G",
          "quantity": 500,
          "unit": "g",
          "mrp": 55.0,
          "sellingPrice": 52.0,
          "gst": 0,
          "stock": 250,
          "barcode": "DAI003500"
        }
      ],
      "voiceMetadata": {
        "keywords": ["dahi", "curd", "yogurt", "दही"],
        "aliases": ["dahi", "sweet dahi"],
        "phonetics": ["duh-hee", "kurd"],
        "regionalVariants": ["dahi", "perugu"],
        "hindiKeywords": ["दही", "ताजा दही", "अमूल दही"]
      }
    },
    {
      "productId": "DAI_004",
      "name": "Paneer",
      "hindiName": "पनीर",
      "brand": "Generic",
      "category": "dairy",
      "productType": "packaged",
      "description": "Fresh Indian cottage cheese",
      "unit": "g",
      "unitType": "weight",
      "variants": [
        {
          "variantId": "DAI_004_200G",
          "quantity": 200,
          "unit": "g",
          "mrp": 180.0,
          "sellingPrice": 175.0,
          "gst": 18,
          "stock": 150,
          "barcode": "DAI004200"
        },
        {
          "variantId": "DAI_004_500G",
          "quantity": 500,
          "unit": "g",
          "mrp": 420.0,
          "sellingPrice": 410.0,
          "gst": 18,
          "stock": 80,
          "barcode": "DAI004500"
        }
      ],
      "voiceMetadata": {
        "keywords": ["paneer", "cheese", "cottage cheese", "पनीर"],
        "aliases": ["panir", "fresh cheese"],
        "phonetics": ["puh-neer", "cheez"],
        "regionalVariants": ["paneer", "chikku"],
        "hindiKeywords": ["पनीर", "ताजा पनीर", "सफेद पनीर"]
      }
    },
    {
      "productId": "DAI_005",
      "name": "Ghee",
      "hindiName": "घी",
      "brand": "Generic",
      "category": "dairy",
      "productType": "packaged",
      "description": "Pure clarified butter ghee",
      "unit": "ml",
      "unitType": "volume",
      "variants": [
        {
          "variantId": "DAI_005_100ML",
          "quantity": 100,
          "unit": "ml",
          "mrp": 120.0,
          "sellingPrice": 115.0,
          "gst": 18,
          "stock": 200,
          "barcode": "DAI005100"
        },
        {
          "variantId": "DAI_005_500ML",
          "quantity": 500,
          "unit": "ml",
          "mrp": 580.0,
          "sellingPrice": 560.0,
          "gst": 18,
          "stock": 80,
          "barcode": "DAI005500"
        }
      ],
      "voiceMetadata": {
        "keywords": ["ghee", "clarified butter", "घी"],
        "aliases": ["ghee", "pure ghee"],
        "phonetics": ["gee", "klar-i-fide but-ur"],
        "regionalVariants": ["ghee", "ney"],
        "hindiKeywords": ["घी", "शुद्ध घी", "गाय का घी"]
      }
    },
    {
      "productId": "DAI_006",
      "name": "Mozzarella Cheese",
      "hindiName": "मोज़ेरेला चीज़",
      "brand": "Generic",
      "category": "dairy",
      "productType": "packaged",
      "description": "Soft mozzarella cheese",
      "unit": "g",
      "unitType": "weight",
      "variants": [
        {
          "variantId": "DAI_006_250G",
          "quantity": 250,
          "unit": "g",
          "mrp": 250.0,
          "sellingPrice": 240.0,
          "gst": 18,
          "stock": 100,
          "barcode": "DAI006250"
        }
      ],
      "voiceMetadata": {
        "keywords": ["mozzarella", "cheese", "मोज़ेरेला"],
        "aliases": ["mozerella", "soft cheese"],
        "phonetics": ["moz-uh-rel-uh", "cheez"],
        "regionalVariants": ["mozzarella", "soft cheese"],
        "hindiKeywords": ["मोज़ेरेला", "सॉफ्ट चीज़", "पिज़्जा चीज़"]
      }
    },
    {
      "productId": "RIC_001",
      "name": "Basmati Rice",
      "hindiName": "बासमती चावल",
      "brand": "Generic",
      "category": "rice",
      "productType": "packaged",
      "description": "Long grain basmati rice",
      "unit": "kg",
      "unitType": "weight",
      "variants": [
        {
          "variantId": "RIC_001_1KG",
          "quantity": 1,
          "unit": "kg",
          "mrp": 90.0,
          "sellingPrice": 85.0,
          "gst": 0,
          "stock": 400,
          "barcode": "RIC001001"
        },
        {
          "variantId": "RIC_001_5KG",
          "quantity": 5,
          "unit": "kg",
          "mrp": 450.0,
          "sellingPrice": 425.0,
          "gst": 0,
          "stock": 150,
          "barcode": "RIC001005"
        }
      ],
      "voiceMetadata": {
        "keywords": ["basmati", "rice", "chawal", "बासमती चावल"],
        "aliases": ["basmati chawal", "long grain"],
        "phonetics": ["buz-muh-tee", "ryes"],
        "regionalVariants": ["basmati", "basmoti"],
        "hindiKeywords": ["बासमती चावल", "बासमती", "लंबे दाने"]
      }
    },
    {
      "productId": "RIC_002",
      "name": "White Rice",
      "hindiName": "सफेद चावल",
      "brand": "Generic",
      "category": "rice",
      "productType": "packaged",
      "description": "Regular polished white rice",
      "unit": "kg",
      "unitType": "weight",
      "variants": [
        {
          "variantId": "RIC_002_1KG",
          "quantity": 1,
          "unit": "kg",
          "mrp": 60.0,
          "sellingPrice": 55.0,
          "gst": 0,
          "stock": 500,
          "barcode": "RIC002001"
        },
        {
          "variantId": "RIC_002_10KG",
          "quantity": 10,
          "unit": "kg",
          "mrp": 600.0,
          "sellingPrice": 550.0,
          "gst": 0,
          "stock": 100,
          "barcode": "RIC002010"
        }
      ],
      "voiceMetadata": {
        "keywords": ["rice", "white rice", "chawal", "सफेद चावल"],
        "aliases": ["ordinary rice", "common rice"],
        "phonetics": ["ryes", "hwite ryes"],
        "regionalVariants": ["chawal", "sada chawal"],
        "hindiKeywords": ["चावल", "सफेद चावल", "सादे चावल"]
      }
    },
    {
      "productId": "RIC_003",
      "name": "Brown Rice",
      "hindiName": "भूरा चावल",
      "brand": "Generic",
      "category": "rice",
      "productType": "packaged",
      "description": "Nutritious brown rice",
      "unit": "kg",
      "unitType": "weight",
      "variants": [
        {
          "variantId": "RIC_003_1KG",
          "quantity": 1,
          "unit": "kg",
          "mrp": 75.0,
          "sellingPrice": 70.0,
          "gst": 0,
          "stock": 200,
          "barcode": "RIC003001"
        }
      ],
      "voiceMetadata": {
        "keywords": ["brown rice", "chawal", "भूरा चावल"],
        "aliases": ["whole grain rice", "nutri rice"],
        "phonetics": ["broun ryes", "bhoora chawal"],
        "regionalVariants": ["brown rice", "poori chawal"],
        "hindiKeywords": ["भूरा चावल", "पूरा चावल", "स्वास्थ्य"]
      }
    },
    {
      "productId": "FLO_001",
      "name": "Wheat Flour (Atta)",
      "hindiName": "गेहूं का आटा",
      "brand": "Aashirvaad",
      "category": "flour",
      "productType": "packaged",
      "description": "Whole wheat flour",
      "unit": "kg",
      "unitType": "weight",
      "variants": [
        {
          "variantId": "FLO_001_1KG",
          "quantity": 1,
          "unit": "kg",
          "mrp": 42.0,
          "sellingPrice": 40.0,
          "gst": 0,
          "stock": 400,
          "barcode": "FLO001001"
        },
        {
          "variantId": "FLO_001_5KG",
          "quantity": 5,
          "unit": "kg",
          "mrp": 210.0,
          "sellingPrice": 200.0,
          "gst": 0,
          "stock": 200,
          "barcode": "FLO001005"
        }
      ],
      "voiceMetadata": {
        "keywords": ["atta", "flour", "wheat flour", "आटा"],
        "aliases": ["gehun atta", "whole wheat"],
        "phonetics": ["uh-tuh", "flour"],
        "regionalVariants": ["atta", "maida"],
        "hindiKeywords": ["आटा", "गेहूं का आटा", "सफेद आटा"]
      }
    },
    {
      "productId": "PUL_001",
      "name": "Arhar Dal (Toor Dal)",
      "hindiName": "अरहर दाल",
      "brand": "Generic",
      "category": "pulses",
      "productType": "packaged",
      "description": "Split pigeon peas",
      "unit": "kg",
      "unitType": "weight",
      "variants": [
        {
          "variantId": "PUL_001_1KG",
          "quantity": 1,
          "unit": "kg",
          "mrp": 120.0,
          "sellingPrice": 115.0,
          "gst": 5,
          "stock": 300,
          "barcode": "PUL001001"
        }
      ],
      "voiceMetadata": {
        "keywords": ["arhar dal", "toor dal", "दाल", "अरहर दाल"],
        "aliases": ["tuvar dal", "pigeon peas"],
        "phonetics": ["ar-hur dal", "toor dal"],
        "regionalVariants": ["arhar dal", "tuvar dal"],
        "hindiKeywords": ["अरहर दाल", "दाल", "दलहन"]
      }
    },
    {
      "productId": "PUL_002",
      "name": "Moong Dal",
      "hindiName": "मूंग दाल",
      "brand": "Generic",
      "category": "pulses",
      "productType": "packaged",
      "description": "Split mung beans",
      "unit": "kg",
      "unitType": "weight",
      "variants": [
        {
          "variantId": "PUL_002_1KG",
          "quantity": 1,
          "unit": "kg",
          "mrp": 100.0,
          "sellingPrice": 95.0,
          "gst": 5,
          "stock": 350,
          "barcode": "PUL002001"
        }
      ],
      "voiceMetadata": {
        "keywords": ["moong dal", "mung dal", "दाल", "मूंग दाल"],
        "aliases": ["mung beans", "green dal"],
        "phonetics": ["moong dal", "mung dal"],
        "regionalVariants": ["moong", "pesarattu"],
        "hindiKeywords": ["मूंग दाल", "दाल", "हरी दाल"]
      }
    },
    {
      "productId": "PUL_003",
      "name": "Urad Dal",
      "hindiName": "उड़द दाल",
      "brand": "Generic",
      "category": "pulses",
      "productType": "packaged",
      "description": "Split black gram",
      "unit": "kg",
      "unitType": "weight",
      "variants": [
        {
          "variantId": "PUL_003_1KG",
          "quantity": 1,
          "unit": "kg",
          "mrp": 110.0,
          "sellingPrice": 105.0,
          "gst": 5,
          "stock": 280,
          "barcode": "PUL003001"
        }
      ],
      "voiceMetadata": {
        "keywords": ["urad dal", "black gram", "दाल", "उड़द दाल"],
        "aliases": ["urid dal", "black lentil"],
        "phonetics": ["oo-rad dal", "black gram"],
        "regionalVariants": ["urad", "minumulu"],
        "hindiKeywords": ["उड़द दाल", "दाल", "काली दाल"]
      }
    }
  ],
  "qualityMetrics": {
    "gatesPass": true,
    "uniqueProducts": 45,
    "avgVariantsPerProduct": 2.1,
    "priceRangeValidation": "PASS",
    "voiceMetadataCompleteness": 100,
    "hindiLocalizationCoverage": 100
  },
  "notes": "Batch 1 contains 45 base vegetables with realistic Indian kirana pricing. Village-first optimization applied. All products are common, recognizable items suitable for voice commerce."
}
